CHANGELOG.txt
LICENCE.txt
MANIFEST.in
README.txt
setup.py
datapredictor/__init__.py
datapredictor.egg-info/PKG-INFO
datapredictor.egg-info/SOURCES.txt
datapredictor.egg-info/dependency_links.txt
datapredictor.egg-info/requires.txt
datapredictor.egg-info/top_level.txt